elib/__init__.py
elib/console.py
elib/custom_random.py
elib/downloader.py
elib/exe_version.py
elib/hash_.py
elib/known_folders.py
elib/paste.py
elib/path.py
elib/pretty.py
elib/repo.py
elib/resource_path.py
elib/run.py
elib/sentry.py
elib/settings.py
elib/tts.py
elib/config/__init__.py
elib/config/config.py
elib/config/property.py
elib/config/yaml_config.py
elib/updater/__init__.py
elib/updater/_github.py
elib/updater/_updater.py
test/__init__.py
test/conftest.py
test/test_console.py
test/test_download.py
test/test_exe_version.py
test/test_find_exe.py
test/test_hash.py
test/test_imports.py
test/test_known_folders.py
test/test_paste.py
test/test_path.py
test/test_pretty.py
test/test_random.py
test/test_resource_path.py
test/test_run.py
test/test_sentry.py
test/test_tts.py
elib-2018.11.22.1.dist-info/LICENSE
elib-2018.11.22.1.dist-info/METADATA
elib-2018.11.22.1.dist-info/WHEEL
elib-2018.11.22.1.dist-info/top_level.txt
elib-2018.11.22.1.dist-info/RECORD
