Metadata-Version: 2.1
Name: elib
Version: 2018.11.22.1
Summary: UNKNOWN
Home-page: UNKNOWN
License: MIT
Platform: UNKNOWN
Classifier: Development Status :: 3 - Alpha
Classifier: Environment :: Win32 (MS Windows)
Classifier: Intended Audience :: Developers
Classifier: Natural Language :: English
Classifier: Operating System :: Microsoft :: Windows :: Windows 7
Classifier: Operating System :: Microsoft :: Windows :: Windows 8
Classifier: Operating System :: Microsoft :: Windows :: Windows 8.1
Classifier: Operating System :: Microsoft :: Windows :: Windows 10
Classifier: License :: OSI Approved :: MIT License
Classifier: Programming Language :: Python :: 3.6
Classifier: Programming Language :: Python :: 3.7
Classifier: Topic :: Utilities
Requires-Python: >=3.6
Requires-Dist: configobj
Requires-Dist: delegator.py
Requires-Dist: everett
Requires-Dist: pyyaml
Requires-Dist: gtts
Requires-Dist: pefile
Requires-Dist: humanize
Requires-Dist: gitpython
Requires-Dist: click
Requires-Dist: tqdm
Requires-Dist: packaging
Requires-Dist: raven
Requires-Dist: certifi
